WPTextSpinner/CommandLine.py
WPTextSpinner/__init__.py
WPTextSpinner/Engine/PostService.py
WPTextSpinner/Engine/TextSpinner.py
WPTextSpinner/Engine/__init__.py
WPTextSpinner/Utils/Constants.py
WPTextSpinner/Utils/Database.py
WPTextSpinner/Utils/Logger.py
WPTextSpinner/Utils/__init__.py
WPTextSpinner-2.dist-info/DESCRIPTION.rst
WPTextSpinner-2.dist-info/METADATA
WPTextSpinner-2.dist-info/RECORD
WPTextSpinner-2.dist-info/WHEEL
WPTextSpinner-2.dist-info/entry_points.txt
WPTextSpinner-2.dist-info/metadata.json
WPTextSpinner-2.dist-info/top_level.txt
